COPYING.txt
MANIFEST.in
README.rst
fplib.cpp
fplib.pyx
lastmatch.py
setup.py
fplib/include/FingerprintExtractor.h
fplib/src/CircularArray.h
fplib/src/Filter.cpp
fplib/src/Filter.h
fplib/src/FingerprintExtractor.cpp
fplib/src/FloatingAverage.h
fplib/src/OptFFT.cpp
fplib/src/OptFFT.h
fplib/src/fp_helper_fun.h
lastfp/__init__.py
pylastfp.egg-info/PKG-INFO
pylastfp.egg-info/SOURCES.txt
pylastfp.egg-info/dependency_links.txt
pylastfp.egg-info/requires.txt
pylastfp.egg-info/top_level.txt