Metadata-Version: 1.0
Name: pylastfp
Version: 0.6
Summary: bindings for Last.fm's acoustic fingerprinting (fplib)
Home-page: http://github.com/sampsyo/pylastfp/
Author: Adrian Sampson
Author-email: adrian@radbox.org
License: LGPL
Platform: ALL
Classifier: Topic :: Multimedia :: Sound/Audio :: Analysis
Classifier: License :: OSI Approved :: GNU Library or Lesser General Public License (LGPL)
Classifier: Development Status :: 4 - Beta
Classifier: Intended Audience :: Developers
